{
  "sku": "bravistawash",
  "attributes": {
    "Brightness": 3,
    "Body": 5,
    "Aroma": 4,
    "Complexity": 5,
    "Balance": 5,
    "Sweetness": 5
  },
  "flavors": {
    "Spicy": 1,
    "Chocolaty": 1,
    "Nutty": 1,
    "Buttery": 3,
    "Fruity": 4,
    "Flowery": 1,
    "Winey": 1,
    "Earthy": 1
  },
  "specifications": {
    "Category": "Conventional",
    "Country": "Brazil",
    "Local Region": "Minas Gerais – Nepomuceno Town",
    "Process": "Washed",
    "Variety": "Yellow Bourbon",
    "Altitude (meters)": "900 - 1,300 masl",
    "Harvest": "May - September",
    "Organic Certification": "No",
    "Fair Trade": "No",
    "Rainforest Alliance Certified": "No",
    "Decaffeinated": "No"
  },
  "description": "Bela Vista Farm: Excellence in South Minas Coffee\n\n\nSituated in the south of Minas, Bela Vista farm thrives in a distinctive micro-region known for producing exceptional highland coffee. This family-owned, traditional estate combines time-honored knowledge with cutting-edge agricultural techniques to achieve a consistent and recognizably high-quality coffee. The farm uses rigerous cultivation practices while maintaining complete traceability throughout the production process.\n\n\nBeyond coffee production, Bela Vista demonstrates its community commitment by funding a primary school serving both workers' children and the surrounding rural community.\n \n\nCupping Notes: Fazenda Bela Vista Washed Yellow Bourbon has notes of red fruit, mild acidity, and a creamy body.\n \nTry before you stock up with a 1/2lb sample!!"
}